cookesgot/__init__.py
cookesgot/main.py
cookiesgetr/__init__.py
cookiesgetr/main.py
fmfocus/__init__.py
fmfocus/main.py
cookiesgetr-0.1.0.dist-info/METADATA
cookiesgetr-0.1.0.dist-info/WHEEL
cookiesgetr-0.1.0.dist-info/top_level.txt
cookiesgetr-0.1.0.dist-info/RECORD
